src/__init__.py
src/app.py
src/common.py
src/debug_app.py
src/draw_line.py
src/draw_roi.py
src/draw_template.py
src/hough_lines.py
src/layout.py
src/metric.py
src/structure.py
src/table_ocr.py
src/PaddleOCR/__init__.py
src/PaddleOCR/paddleocr.py
src/PaddleOCR/run.py
src/PaddleOCR/setup.py
src/PaddleOCR/test.py
src/PaddleOCR/PPOCRLabel/PPOCRLabel.py
src/PaddleOCR/PPOCRLabel/__init__.py
src/PaddleOCR/PPOCRLabel/gen_ocr_train_val_test.py
src/PaddleOCR/PPOCRLabel/setup.py
src/PaddleOCR/PPOCRLabel/libs/__init__.py
src/PaddleOCR/PPOCRLabel/libs/autoDialog.py
src/PaddleOCR/PPOCRLabel/libs/canvas.py
src/PaddleOCR/PPOCRLabel/libs/colorDialog.py
src/PaddleOCR/PPOCRLabel/libs/constants.py
src/PaddleOCR/PPOCRLabel/libs/create_ml_io.py
src/PaddleOCR/PPOCRLabel/libs/dataPartitionDialog.py
src/PaddleOCR/PPOCRLabel/libs/editinlist.py
src/PaddleOCR/PPOCRLabel/libs/hashableQListWidgetItem.py
src/PaddleOCR/PPOCRLabel/libs/keyDialog.py
src/PaddleOCR/PPOCRLabel/libs/labelColor.py
src/PaddleOCR/PPOCRLabel/libs/labelDialog.py
src/PaddleOCR/PPOCRLabel/libs/resources.py
src/PaddleOCR/PPOCRLabel/libs/settings.py
src/PaddleOCR/PPOCRLabel/libs/shape.py
src/PaddleOCR/PPOCRLabel/libs/stringBundle.py
src/PaddleOCR/PPOCRLabel/libs/toolBar.py
src/PaddleOCR/PPOCRLabel/libs/unique_label_qlist_widget.py
src/PaddleOCR/PPOCRLabel/libs/ustr.py
src/PaddleOCR/PPOCRLabel/libs/utils.py
src/PaddleOCR/PPOCRLabel/libs/zoomWidget.py
src/PaddleOCR/StyleText/__init__.py
src/PaddleOCR/StyleText/arch/__init__.py
src/PaddleOCR/StyleText/arch/base_module.py
src/PaddleOCR/StyleText/arch/decoder.py
src/PaddleOCR/StyleText/arch/encoder.py
src/PaddleOCR/StyleText/arch/spectral_norm.py
src/PaddleOCR/StyleText/arch/style_text_rec.py
src/PaddleOCR/StyleText/engine/__init__.py
src/PaddleOCR/StyleText/engine/corpus_generators.py
src/PaddleOCR/StyleText/engine/predictors.py
src/PaddleOCR/StyleText/engine/style_samplers.py
src/PaddleOCR/StyleText/engine/synthesisers.py
src/PaddleOCR/StyleText/engine/text_drawers.py
weiming_demo-1.0.1.dist-info/LICENSE
weiming_demo-1.0.1.dist-info/METADATA
weiming_demo-1.0.1.dist-info/WHEEL
weiming_demo-1.0.1.dist-info/top_level.txt
weiming_demo-1.0.1.dist-info/RECORD
