Metadata-Version: 2.1
Name: weiming-demo
Version: 1.0.1
Summary: Demo for parsing
Home-page: https://upload.pypi.org/legacy
Author: weiming.li
Author-email: silang1225@126.com
Classifier: Programming Language :: Python :: 3
License-File: LICENSE
